README.txt
__init__.py
setup.py
workingenv.py
examples/tg-0.9.txt
examples/tg-example.txt
workingenv.py.egg-info/PKG-INFO
workingenv.py.egg-info/SOURCES.txt
workingenv.py.egg-info/dependency_links.txt
workingenv.py.egg-info/entry_points.txt
workingenv.py.egg-info/not-zip-safe
workingenv.py.egg-info/top_level.txt
