Metadata-Version: 1.0
Name: workingenv.py
Version: 0.6.4
Summary: Tool to create isolated Python environment
Home-page: http://cheeseshop.python.org/pypi/workingenv.py
Author: Ian Bicking
Author-email: ianb@colorstudy.com
License: MIT
Keywords: setuptools deployment installation distutils
Platform: UNKNOWN
Classifier: Development Status :: 5 - Production/Stable
Classifier: Intended Audience :: Developers
Classifier: License :: OSI Approved :: MIT License
